model2name/__init__.py
model2name/brand_map.py
model2name/handle_data.py
model2name/model2name.py
model2name/data/360shouji.json
model2name/data/apple_all.json
model2name/data/apple_all_en.json
model2name/data/apple_cn.json
model2name/data/asus.json
model2name/data/asus_cn.json
model2name/data/asus_en.json
model2name/data/blackshark.json
model2name/data/blackshark_en.json
model2name/data/coolpad.json
model2name/data/google.json
model2name/data/honor_cn.json
model2name/data/honor_global_en.json
model2name/data/huawei_cn.json
model2name/data/huawei_global_en.json
model2name/data/lenovo.json
model2name/data/letv.json
model2name/data/meizu.json
model2name/data/meizu_en.json
model2name/data/mitv_cn.json
model2name/data/mitv_global_en.json
model2name/data/motorola.json
model2name/data/nokia.json
model2name/data/nothing.json
model2name/data/nubia.json
model2name/data/oneplus.json
model2name/data/oneplus_en.json
model2name/data/oppo_cn.json
model2name/data/oppo_global_en.json
model2name/data/realme_cn.json
model2name/data/realme_global_en.json
model2name/data/samsung_cn.json
model2name/data/samsung_global_en.json
model2name/data/smartisan.json
model2name/data/sony_cn.json
model2name/data/vivo_cn.json
model2name/data/vivo_global_en.json
model2name/data/xiaomi-wear.json
model2name/data/xiaomi.json
model2name/data/xiaomi_en.json
model2name/data/zhixuan.json
model2name/data/zte.json
brand_model2name-0.0.10.dist-info/LICENSE
brand_model2name-0.0.10.dist-info/METADATA
brand_model2name-0.0.10.dist-info/WHEEL
brand_model2name-0.0.10.dist-info/top_level.txt
brand_model2name-0.0.10.dist-info/RECORD
