Metadata-Version: 2.1
Name: brand-model2name
Version: 0.0.10
Summary: A simple package that takes a brand name as input and returns the corresponding model name.
Home-page: https://github.com/hbx286/brand-model2name.git
Author: hbx286
Author-email: hbxmail429@gmail.com
License: MIT
Classifier: License :: OSI Approved :: Attribution Assurance License
Classifier: Programming Language :: Python
Classifier: Programming Language :: Python :: 3
Classifier: Programming Language :: Python :: 3.8
Classifier: Programming Language :: Python :: Implementation :: CPython
Classifier: Programming Language :: Python :: Implementation :: PyPy
Requires-Python: >=3.8.0
License-File: LICENSE
